{
  "id": "board_page",
  "label": "Board Page",
  "repeatable": false,
  "status": true,
  "json": {
    "Main": {
      "image": {
        "type": "Image",
        "config": {
          "label": "Image",
          "constraint": {},
          "thumbnails": []
        }
      },
      "slices": {
        "type": "Slices",
        "fieldset": "Slice Zone",
        "config": {
          "choices": {
            "section": {
              "type": "SharedSlice"
            }
          }
        }
      }
    }
  }
}